{"portals": [{"lat": 13.21449, "name": "Zug Rarit\u00e4t", "long": 47.425084}, {"lat": 13.217926, "name": "Salzburg 1", "long": 47.418099}, {"lat": 13.219627, "name": "Bahnhof Bischofshofen", "long": 47.418041}, {"lat": 13.217415, "name": "Alte Post Bischofshofen", "long": 47.416053}, {"lat": 13.207937, "name": "Schanze Bischofshofen", "long": 47.415337}, {"lat": 13.207691, "name": "Schwimmbad St. Johann", "long": 47.351921}, {"lat": 13.202141, "name": "War Dead", "long": 47.34902}, {"lat": 13.201563, "name": "Moderne Skulptur St. Johann", "long": 47.347263}, {"lat": 13.203166, "name": "Amade", "long": 47.309641}, {"lat": 13.308062, "name": "Riesenrad in Wagrain", "long": 47.334088}, {"lat": 13.30337, "name": "Wagrein Kirche", "long": 47.33406}, {"lat": 13.297515, "name": "Sonnenuhr in Wagrain", "long": 47.334892}, {"lat": 13.296887, "name": "Uhr in Wagrain", "long": 47.334554}, {"lat": 13.322143, "name": "Hergott Schwaighof", "long": 47.353899}, {"lat": 13.3, "name": "St.Vinzenz Friedenskirche am H", "long": 47.383333}, {"lat": 13.306771, "name": "WWII Monument", "long": 47.416274}, {"lat": 13.307456, "name": "Kirche H\u00fcttau", "long": 47.415955}, {"lat": 13.398607, "name": "Schattbach Kapelle", "long": 47.419686}, {"lat": 13.397339, "name": "Kreistbrunnen", "long": 47.416151}, {"lat": 13.396871, "name": "Geheimer B\u00f6rd Brunnen Eben", "long": 47.415984}, {"lat": 13.393875, "name": "Weitgasser Hund", "long": 47.409139}, {"lat": 13.394436, "name": "Altes Haus Eben", "long": 47.408122}, {"lat": 13.394667, "name": "Kirche Eben", "long": 47.407515}, {"lat": 13.39551, "name": "Olympia Platz Eben", "long": 47.407325}, {"lat": 13.396316, "name": "Bahnhof Eben", "long": 47.406424}, {"lat": 13.397858, "name": "Naturschutzgebiet Eben", "long": 47.400623}, {"lat": 13.396947, "name": "Badesee Eben", "long": 47.399829}, {"lat": 13.408669, "name": "Moosalm Eben", "long": 47.400268}, {"lat": 13.392398, "name": "Altes Haus H\u00f6ch", "long": 47.389398}, {"lat": 13.411591, "name": "Laudersbach Dead Monument", "long": 47.389083}, {"lat": 13.417938, "name": "Laudersbach Dead Monument", "long": 47.38466}, {"lat": 13.42548, "name": "Heimathaus Altenmarkt", "long": 47.380249}, {"lat": 13.425139, "name": "Altenmarkt Kirche", "long": 47.380034}, {"lat": 13.423558, "name": "Post Office Altenmarkt", "long": 47.378224}, {"lat": 13.423699, "name": "Pfarrhof Altenmarkt", "long": 47.377817}, {"lat": 13.422049, "name": "Altes H\u00e4uschen Altenmarkt", "long": 47.379064}, {"lat": 13.417551, "name": "Hans Schneider Moden", "long": 47.381053}, {"lat": 13.41368, "name": "Urbisgut Altenmarkt", "long": 47.380016}, {"lat": 13.410358, "name": "Therme Altenmarkt", "long": 47.380584}, {"lat": 13.384888, "name": "Chapel Reitdorf", "long": 47.378871}, {"lat": 13.392464, "name": "Reitdorf Pichlerturm", "long": 47.374946}, {"lat": 13.389493, "name": "Tenne Reitdorf", "long": 47.372882}, {"lat": 13.389134, "name": "Gemeindeamt Reitdorf", "long": 47.371907}, {"lat": 13.382816, "name": "Reitecksee Reitdorf", "long": 47.37307}, {"lat": 13.389553, "name": "Flachau (136)", "long": 47.362629}, {"lat": 13.368392, "name": "Schloss Hoech", "long": 47.367029}, {"lat": 13.389096, "name": "Flachau (134)", "long": 47.358239}, {"lat": 13.388006, "name": "Flachau (113)", "long": 47.354956}, {"lat": 13.387665, "name": "Yetibar Flachau", "long": 47.354674}, {"lat": 13.392217, "name": "Flachau (118)", "long": 47.353881}, {"lat": 13.393522, "name": "Hofstadl Flachau", "long": 47.352866}, {"lat": 13.394166, "name": "Flachau (78)", "long": 47.351666}, {"lat": 13.385499, "name": "Achterjet Flachau", "long": 47.353927}, {"lat": 13.39179, "name": "Schusterh\u00e4usl Flachau", "long": 47.347896}, {"lat": 13.391802, "name": "Hoagascht Flachau", "long": 47.347502}, {"lat": 13.394651, "name": "Flachau (90)", "long": 47.346586}, {"lat": 13.363009, "name": "Kristall Wagrain", "long": 47.359905}, {"lat": 13.392168, "name": "Lift Flachauwinkl", "long": 47.296825}, {"lat": 13.448831, "name": "Unterbergalm Zauchensee", "long": 47.291774}, {"lat": 13.423206, "name": "Gipfelkreuz Lacken Kogel", "long": 47.326568}, {"lat": 13.391948, "name": "Flachau (77)", "long": 47.344015}, {"lat": 13.394528, "name": "Kirche Flachau", "long": 47.342961}, {"lat": 13.426411, "name": "Hofi Lift Altenmarkt", "long": 47.361488}, {"lat": 13.428712, "name": "Green Party Barrel", "long": 47.370166}, {"lat": 13.429365, "name": "Rectangualr Fountain 1", "long": 47.37044}, {"lat": 13.467135, "name": "Zum jungen R\u00f6mer Radstadt", "long": 47.375671}, {"lat": 13.472219, "name": "Antonius Kapelle Radstadt", "long": 47.384442}, {"lat": 13.472214, "name": "Alte Villa Radstadt", "long": 47.386367}, {"lat": 13.464426, "name": "Radstadt Pfarrkirche", "long": 47.385265}, {"lat": 13.457733, "name": "Radstadt Zum Hirschen", "long": 47.385185}, {"lat": 13.442243, "name": "Castle Tandalier", "long": 47.384268}, {"lat": 13.462718, "name": "B\u00fccherschrank Radstadt", "long": 47.384984}, {"lat": 13.463548, "name": "Burg Radstadt", "long": 47.384955}, {"lat": 13.462867, "name": "2nd World War Monument", "long": 47.384756}, {"lat": 13.478775, "name": "Gipfelkreuz Rossbrand", "long": 47.415447}, {"lat": 13.494532, "name": "Seitenalm Radstadt", "long": 47.388241}, {"lat": 13.397548, "name": "Reitdorf Altes Bauernhaus", "long": 47.379492}, {"lat": 13.3921, "name": "Sunshine Lift Flachau", "long": 47.297029}]}
